isa_mcp_cli-1.0.0.dist-info/licenses/LICENSE
utils/mcp_cli.py
utils/mcp_client.py
isa_mcp_cli-1.0.0.dist-info/METADATA
isa_mcp_cli-1.0.0.dist-info/WHEEL
isa_mcp_cli-1.0.0.dist-info/entry_points.txt
isa_mcp_cli-1.0.0.dist-info/top_level.txt
isa_mcp_cli-1.0.0.dist-info/RECORD
