Metadata-Version: 2.4
Name: isa-mcp-cli
Version: 1.0.0
Summary: ISA MCP CLI - Comprehensive command-line interface for MCP server with RAG capabilities
Author-email: ISA Team <info@isa-mcp.com>
License: MIT
Project-URL: Homepage, https://github.com/yourusername/isA_MCP
Project-URL: Documentation, https://github.com/yourusername/isA_MCP/blob/main/README.md
Project-URL: Repository, https://github.com/yourusername/isA_MCP
Project-URL: Issues, https://github.com/yourusername/isA_MCP/issues
Keywords: mcp,cli,rag,knowledge,ai,llm
Classifier: Development Status :: 4 - Beta
Classifier: Intended Audience :: Developers
Classifier: Topic :: Software Development :: Libraries :: Python Modules
Classifier: License :: OSI Approved :: MIT License
Classifier: Programming Language :: Python :: 3
Classifier: Programming Language :: Python :: 3.8
Classifier: Programming Language :: Python :: 3.9
Classifier: Programming Language :: Python :: 3.10
Classifier: Programming Language :: Python :: 3.11
Requires-Python: >=3.8
License-File: LICENSE
Requires-Dist: aiohttp>=3.8.0
Requires-Dist: rich>=13.0.0
Requires-Dist: prompt-toolkit>=3.0.0
Provides-Extra: dev
Requires-Dist: pytest>=7.0.0; extra == "dev"
Requires-Dist: black>=22.0.0; extra == "dev"
Requires-Dist: mypy>=0.990; extra == "dev"
Dynamic: license-file
